[
  {
    "id": "tshirt-classic-white",
    "slug": "classic-white-tee",
    "category": "t-shirts",
    "title": "Classic White T-Shirt",
    "description": "Timeless white cotton tee",
    "price": 24.99,
    "color": "white",
    "size": "M",
    "popularity": 95,
    "gender": "women"
  },
  {
    "id": "tshirt-navy-blue",
    "slug": "navy-blue-tee",
    "category": "t-shirts",
    "title": "Navy Blue T-Shirt",
    "description": "Deep navy blue cotton tee",
    "price": 24.99,
    "color": "blue",
    "size": "L",
    "popularity": 88,
    "gender": "men"
  },
  {
    "id": "tshirt-black-crew",
    "slug": "black-crew-tee",
    "category": "t-shirts",
    "title": "Black Crew Neck T-Shirt",
    "description": "Classic black crew neck",
    "price": 26.99,
    "color": "black",
    "size": "M",
    "popularity": 92,
    "gender": "girls"
  },
  {
    "id": "tshirt-gray-vneck",
    "slug": "gray-vneck-tee",
    "category": "t-shirts",
    "title": "Gray V-Neck T-Shirt",
    "description": "Soft gray v-neck style",
    "price": 27.99,
    "color": "gray",
    "size": "L",
    "popularity": 78,
    "gender": "boys"
  },
  {
    "id": "tshirt-red-pocket",
    "slug": "red-pocket-tee",
    "category": "t-shirts",
    "title": "Red Pocket T-Shirt",
    "description": "Vibrant red with chest pocket",
    "price": 29.99,
    "color": "red",
    "size": "M",
    "popularity": 71,
    "gender": "women"
  },
  {
    "id": "tshirt-green-long",
    "slug": "green-longsleeve-tee",
    "category": "t-shirts",
    "title": "Green Long Sleeve T-Shirt",
    "description": "Forest green long sleeve",
    "price": 32.99,
    "color": "green",
    "size": "XL",
    "popularity": 65,
    "gender": "men"
  },
  {
    "id": "tshirt-white-vneck",
    "slug": "white-vneck-tee",
    "category": "t-shirts",
    "title": "White V-Neck T-Shirt",
    "description": "Clean white v-neck",
    "price": 23.99,
    "color": "white",
    "size": "S",
    "popularity": 85,
    "gender": "girls"
  },
  {
    "id": "tshirt-blue-pocket",
    "slug": "blue-pocket-tee",
    "category": "t-shirts",
    "title": "Blue Pocket T-Shirt",
    "description": "Sky blue with pocket detail",
    "price": 28.99,
    "color": "blue",
    "size": "M",
    "popularity": 82,
    "gender": "boys"
  },
  {
    "id": "tshirt-black-vneck",
    "slug": "black-vneck-tee",
    "category": "t-shirts",
    "title": "Black V-Neck T-Shirt",
    "description": "Sleek black v-neck",
    "price": 25.99,
    "color": "black",
    "size": "L",
    "popularity": 90,
    "gender": "women"
  },
  {
    "id": "tshirt-gray-crew",
    "slug": "gray-crew-tee",
    "category": "t-shirts",
    "title": "Gray Crew Neck T-Shirt",
    "description": "Heather gray classic crew",
    "price": 24.99,
    "color": "gray",
    "size": "M",
    "popularity": 87,
    "gender": "men"
  },
  {
    "id": "tshirt-red-crew",
    "slug": "red-crew-tee",
    "category": "t-shirts",
    "title": "Red Crew Neck T-Shirt",
    "description": "Bold red crew neck",
    "price": 26.99,
    "color": "red",
    "size": "L",
    "popularity": 75,
    "gender": "girls"
  },
  {
    "id": "tshirt-green-crew",
    "slug": "green-crew-tee",
    "category": "t-shirts",
    "title": "Green Crew Neck T-Shirt",
    "description": "Olive green crew neck",
    "price": 25.99,
    "color": "green",
    "size": "M",
    "popularity": 68,
    "gender": "boys"
  },
  {
    "id": "tshirt-white-long",
    "slug": "white-longsleeve-tee",
    "category": "t-shirts",
    "title": "White Long Sleeve T-Shirt",
    "description": "Classic white long sleeve",
    "price": 31.99,
    "color": "white",
    "size": "L",
    "popularity": 80,
    "gender": "women"
  },
  {
    "id": "tshirt-blue-long",
    "slug": "blue-longsleeve-tee",
    "category": "t-shirts",
    "title": "Blue Long Sleeve T-Shirt",
    "description": "Navy blue long sleeve",
    "price": 33.99,
    "color": "blue",
    "size": "XL",
    "popularity": 73,
    "gender": "men"
  },
  {
    "id": "tshirt-black-long",
    "slug": "black-longsleeve-tee",
    "category": "t-shirts",
    "title": "Black Long Sleeve T-Shirt",
    "description": "Black long sleeve cotton",
    "price": 32.99,
    "color": "black",
    "size": "M",
    "popularity": 84,
    "gender": "girls"
  },
  {
    "id": "tshirt-gray-long",
    "slug": "gray-longsleeve-tee",
    "category": "t-shirts",
    "title": "Gray Long Sleeve T-Shirt",
    "description": "Charcoal gray long sleeve",
    "price": 30.99,
    "color": "gray",
    "size": "L",
    "popularity": 70,
    "gender": "boys"
  },
  {
    "id": "tshirt-red-vneck",
    "slug": "red-vneck-tee",
    "category": "t-shirts",
    "title": "Red V-Neck T-Shirt",
    "description": "Cardinal red v-neck",
    "price": 27.99,
    "color": "red",
    "size": "M",
    "popularity": 66,
    "gender": "women"
  },
  {
    "id": "tshirt-green-vneck",
    "slug": "green-vneck-tee",
    "category": "t-shirts",
    "title": "Green V-Neck T-Shirt",
    "description": "Forest green v-neck",
    "price": 26.99,
    "color": "green",
    "size": "S",
    "popularity": 62,
    "gender": "men"
  },
  {
    "id": "tshirt-white-pocket",
    "slug": "white-pocket-tee",
    "category": "t-shirts",
    "title": "White Pocket T-Shirt",
    "description": "White tee with chest pocket",
    "price": 28.99,
    "color": "white",
    "size": "M",
    "popularity": 79,
    "gender": "girls"
  },
  {
    "id": "tshirt-black-pocket",
    "slug": "black-pocket-tee",
    "category": "t-shirts",
    "title": "Black Pocket T-Shirt",
    "description": "Black tee with pocket detail",
    "price": 29.99,
    "color": "black",
    "size": "L",
    "popularity": 86,
    "gender": "boys"
  },
  {
    "id": "tshirt-gray-pocket",
    "slug": "gray-pocket-tee",
    "category": "t-shirts",
    "title": "Gray Pocket T-Shirt",
    "description": "Gray tee with front pocket",
    "price": 27.99,
    "color": "gray",
    "size": "M",
    "popularity": 72,
    "gender": "women"
  },
  {
    "id": "tshirt-blue-crew",
    "slug": "blue-crew-tee",
    "category": "t-shirts",
    "title": "Blue Crew Neck T-Shirt",
    "description": "Royal blue crew neck",
    "price": 25.99,
    "color": "blue",
    "size": "L",
    "popularity": 81,
    "gender": "men"
  },
  {
    "id": "tshirt-green-pocket",
    "slug": "green-pocket-tee",
    "category": "t-shirts",
    "title": "Green Pocket T-Shirt",
    "description": "Green tee with pocket",
    "price": 28.99,
    "color": "green",
    "size": "M",
    "popularity": 64,
    "gender": "girls"
  },
  {
    "id": "tshirt-red-long",
    "slug": "red-longsleeve-tee",
    "category": "t-shirts",
    "title": "Red Long Sleeve T-Shirt",
    "description": "Red long sleeve cotton",
    "price": 34.99,
    "color": "red",
    "size": "XL",
    "popularity": 67,
    "gender": "boys"
  },
  {
    "id": "tshirt-women-100",
    "slug": "women-black-crew-neck-0",
    "category": "t-shirts",
    "title": "Black Crew Neck",
    "description": "Slim Fit black crew neck for women",
    "price": 26.63,
    "color": "black",
    "size": "S",
    "gender": "women",
    "popularity": 57
  },
  {
    "id": "tshirt-women-101",
    "slug": "women-white-v-neck-1",
    "category": "t-shirts",
    "title": "White V-Neck",
    "description": "Regular Fit white v-neck for women",
    "price": 26.95,
    "color": "white",
    "size": "M",
    "gender": "women",
    "popularity": 57
  },
  {
    "id": "tshirt-women-102",
    "slug": "women-blue-henley-2",
    "category": "t-shirts",
    "title": "Blue Henley",
    "description": "Relaxed Fit blue henley for women",
    "price": 29.9,
    "color": "blue",
    "size": "L",
    "gender": "women",
    "popularity": 82
  },
  {
    "id": "tshirt-women-103",
    "slug": "women-red-polo-3",
    "category": "t-shirts",
    "title": "Red Polo",
    "description": "Athletic Fit red polo for women",
    "price": 24.49,
    "color": "red",
    "size": "XL",
    "gender": "women",
    "popularity": 68
  },
  {
    "id": "tshirt-women-104",
    "slug": "women-green-tank-top-4",
    "category": "t-shirts",
    "title": "Green Tank Top",
    "description": "Slim Fit green tank top for women",
    "price": 24.66,
    "color": "green",
    "size": "S",
    "gender": "women",
    "popularity": 77
  },
  {
    "id": "tshirt-women-105",
    "slug": "women-gray-crew-neck-5",
    "category": "t-shirts",
    "title": "Gray Crew Neck",
    "description": "Regular Fit gray crew neck for women",
    "price": 25.8,
    "color": "gray",
    "size": "M",
    "gender": "women",
    "popularity": 84
  },
  {
    "id": "tshirt-women-106",
    "slug": "women-brown-v-neck-6",
    "category": "t-shirts",
    "title": "Brown V-Neck",
    "description": "Relaxed Fit brown v-neck for women",
    "price": 23.21,
    "color": "brown",
    "size": "L",
    "gender": "women",
    "popularity": 90
  },
  {
    "id": "tshirt-women-107",
    "slug": "women-tan-henley-7",
    "category": "t-shirts",
    "title": "Tan Henley",
    "description": "Athletic Fit tan henley for women",
    "price": 23.92,
    "color": "tan",
    "size": "XL",
    "gender": "women",
    "popularity": 67
  },
  {
    "id": "tshirt-women-108",
    "slug": "women-black-polo-8",
    "category": "t-shirts",
    "title": "Black Polo",
    "description": "Slim Fit black polo for women",
    "price": 30.91,
    "color": "black",
    "size": "S",
    "gender": "women",
    "popularity": 63
  },
  {
    "id": "tshirt-women-109",
    "slug": "women-white-tank-top-9",
    "category": "t-shirts",
    "title": "White Tank Top",
    "description": "Regular Fit white tank top for women",
    "price": 32.71,
    "color": "white",
    "size": "M",
    "gender": "women",
    "popularity": 56
  },
  {
    "id": "tshirt-women-110",
    "slug": "women-blue-crew-neck-10",
    "category": "t-shirts",
    "title": "Blue Crew Neck",
    "description": "Relaxed Fit blue crew neck for women",
    "price": 33.01,
    "color": "blue",
    "size": "L",
    "gender": "women",
    "popularity": 70
  },
  {
    "id": "tshirt-women-111",
    "slug": "women-red-v-neck-11",
    "category": "t-shirts",
    "title": "Red V-Neck",
    "description": "Athletic Fit red v-neck for women",
    "price": 31.46,
    "color": "red",
    "size": "XL",
    "gender": "women",
    "popularity": 84
  },
  {
    "id": "tshirt-women-112",
    "slug": "women-green-henley-12",
    "category": "t-shirts",
    "title": "Green Henley",
    "description": "Slim Fit green henley for women",
    "price": 23.39,
    "color": "green",
    "size": "S",
    "gender": "women",
    "popularity": 92
  },
  {
    "id": "tshirt-women-113",
    "slug": "women-gray-polo-13",
    "category": "t-shirts",
    "title": "Gray Polo",
    "description": "Regular Fit gray polo for women",
    "price": 32.01,
    "color": "gray",
    "size": "M",
    "gender": "women",
    "popularity": 82
  },
  {
    "id": "tshirt-men-114",
    "slug": "men-black-crew-neck-0",
    "category": "t-shirts",
    "title": "Black Crew Neck",
    "description": "Slim Fit black crew neck for men",
    "price": 30.1,
    "color": "black",
    "size": "S",
    "gender": "men",
    "popularity": 59
  },
  {
    "id": "tshirt-men-115",
    "slug": "men-white-v-neck-1",
    "category": "t-shirts",
    "title": "White V-Neck",
    "description": "Regular Fit white v-neck for men",
    "price": 23.15,
    "color": "white",
    "size": "M",
    "gender": "men",
    "popularity": 88
  },
  {
    "id": "tshirt-men-116",
    "slug": "men-blue-henley-2",
    "category": "t-shirts",
    "title": "Blue Henley",
    "description": "Relaxed Fit blue henley for men",
    "price": 31.51,
    "color": "blue",
    "size": "L",
    "gender": "men",
    "popularity": 87
  },
  {
    "id": "tshirt-men-117",
    "slug": "men-red-polo-3",
    "category": "t-shirts",
    "title": "Red Polo",
    "description": "Athletic Fit red polo for men",
    "price": 27.14,
    "color": "red",
    "size": "XL",
    "gender": "men",
    "popularity": 63
  },
  {
    "id": "tshirt-men-118",
    "slug": "men-green-tank-top-4",
    "category": "t-shirts",
    "title": "Green Tank Top",
    "description": "Slim Fit green tank top for men",
    "price": 31.13,
    "color": "green",
    "size": "S",
    "gender": "men",
    "popularity": 63
  },
  {
    "id": "tshirt-men-119",
    "slug": "men-gray-crew-neck-5",
    "category": "t-shirts",
    "title": "Gray Crew Neck",
    "description": "Regular Fit gray crew neck for men",
    "price": 32.2,
    "color": "gray",
    "size": "M",
    "gender": "men",
    "popularity": 92
  },
  {
    "id": "tshirt-men-120",
    "slug": "men-brown-v-neck-6",
    "category": "t-shirts",
    "title": "Brown V-Neck",
    "description": "Relaxed Fit brown v-neck for men",
    "price": 27.75,
    "color": "brown",
    "size": "L",
    "gender": "men",
    "popularity": 74
  },
  {
    "id": "tshirt-men-121",
    "slug": "men-tan-henley-7",
    "category": "t-shirts",
    "title": "Tan Henley",
    "description": "Athletic Fit tan henley for men",
    "price": 29.03,
    "color": "tan",
    "size": "XL",
    "gender": "men",
    "popularity": 55
  },
  {
    "id": "tshirt-men-122",
    "slug": "men-black-polo-8",
    "category": "t-shirts",
    "title": "Black Polo",
    "description": "Slim Fit black polo for men",
    "price": 25.01,
    "color": "black",
    "size": "S",
    "gender": "men",
    "popularity": 85
  },
  {
    "id": "tshirt-men-123",
    "slug": "men-white-tank-top-9",
    "category": "t-shirts",
    "title": "White Tank Top",
    "description": "Regular Fit white tank top for men",
    "price": 28.49,
    "color": "white",
    "size": "M",
    "gender": "men",
    "popularity": 66
  },
  {
    "id": "tshirt-men-124",
    "slug": "men-blue-crew-neck-10",
    "category": "t-shirts",
    "title": "Blue Crew Neck",
    "description": "Relaxed Fit blue crew neck for men",
    "price": 34.19,
    "color": "blue",
    "size": "L",
    "gender": "men",
    "popularity": 87
  },
  {
    "id": "tshirt-men-125",
    "slug": "men-red-v-neck-11",
    "category": "t-shirts",
    "title": "Red V-Neck",
    "description": "Athletic Fit red v-neck for men",
    "price": 32.33,
    "color": "red",
    "size": "XL",
    "gender": "men",
    "popularity": 77
  },
  {
    "id": "tshirt-men-126",
    "slug": "men-green-henley-12",
    "category": "t-shirts",
    "title": "Green Henley",
    "description": "Slim Fit green henley for men",
    "price": 34.33,
    "color": "green",
    "size": "S",
    "gender": "men",
    "popularity": 92
  },
  {
    "id": "tshirt-men-127",
    "slug": "men-gray-polo-13",
    "category": "t-shirts",
    "title": "Gray Polo",
    "description": "Regular Fit gray polo for men",
    "price": 29.67,
    "color": "gray",
    "size": "M",
    "gender": "men",
    "popularity": 78
  },
  {
    "id": "tshirt-girls-128",
    "slug": "girls-black-crew-neck-0",
    "category": "t-shirts",
    "title": "Black Crew Neck",
    "description": "Slim Fit black crew neck for girls",
    "price": 25.32,
    "color": "black",
    "size": "XS",
    "gender": "girls",
    "popularity": 63
  },
  {
    "id": "tshirt-girls-129",
    "slug": "girls-white-v-neck-1",
    "category": "t-shirts",
    "title": "White V-Neck",
    "description": "Regular Fit white v-neck for girls",
    "price": 24.31,
    "color": "white",
    "size": "S",
    "gender": "girls",
    "popularity": 55
  },
  {
    "id": "tshirt-girls-130",
    "slug": "girls-blue-henley-2",
    "category": "t-shirts",
    "title": "Blue Henley",
    "description": "Relaxed Fit blue henley for girls",
    "price": 17.93,
    "color": "blue",
    "size": "M",
    "gender": "girls",
    "popularity": 65
  },
  {
    "id": "tshirt-girls-131",
    "slug": "girls-red-polo-3",
    "category": "t-shirts",
    "title": "Red Polo",
    "description": "Athletic Fit red polo for girls",
    "price": 18.9,
    "color": "red",
    "size": "L",
    "gender": "girls",
    "popularity": 67
  },
  {
    "id": "tshirt-girls-132",
    "slug": "girls-green-tank-top-4",
    "category": "t-shirts",
    "title": "Green Tank Top",
    "description": "Slim Fit green tank top for girls",
    "price": 24.89,
    "color": "green",
    "size": "XS",
    "gender": "girls",
    "popularity": 64
  },
  {
    "id": "tshirt-girls-133",
    "slug": "girls-gray-crew-neck-5",
    "category": "t-shirts",
    "title": "Gray Crew Neck",
    "description": "Regular Fit gray crew neck for girls",
    "price": 17.21,
    "color": "gray",
    "size": "S",
    "gender": "girls",
    "popularity": 76
  },
  {
    "id": "tshirt-girls-134",
    "slug": "girls-brown-v-neck-6",
    "category": "t-shirts",
    "title": "Brown V-Neck",
    "description": "Relaxed Fit brown v-neck for girls",
    "price": 23.73,
    "color": "brown",
    "size": "M",
    "gender": "girls",
    "popularity": 75
  },
  {
    "id": "tshirt-girls-135",
    "slug": "girls-tan-henley-7",
    "category": "t-shirts",
    "title": "Tan Henley",
    "description": "Athletic Fit tan henley for girls",
    "price": 19.43,
    "color": "tan",
    "size": "L",
    "gender": "girls",
    "popularity": 71
  },
  {
    "id": "tshirt-girls-136",
    "slug": "girls-black-polo-8",
    "category": "t-shirts",
    "title": "Black Polo",
    "description": "Slim Fit black polo for girls",
    "price": 20.76,
    "color": "black",
    "size": "XS",
    "gender": "girls",
    "popularity": 75
  },
  {
    "id": "tshirt-girls-137",
    "slug": "girls-white-tank-top-9",
    "category": "t-shirts",
    "title": "White Tank Top",
    "description": "Regular Fit white tank top for girls",
    "price": 21.72,
    "color": "white",
    "size": "S",
    "gender": "girls",
    "popularity": 93
  },
  {
    "id": "tshirt-girls-138",
    "slug": "girls-blue-crew-neck-10",
    "category": "t-shirts",
    "title": "Blue Crew Neck",
    "description": "Relaxed Fit blue crew neck for girls",
    "price": 16.56,
    "color": "blue",
    "size": "M",
    "gender": "girls",
    "popularity": 58
  },
  {
    "id": "tshirt-girls-139",
    "slug": "girls-red-v-neck-11",
    "category": "t-shirts",
    "title": "Red V-Neck",
    "description": "Athletic Fit red v-neck for girls",
    "price": 18.88,
    "color": "red",
    "size": "L",
    "gender": "girls",
    "popularity": 86
  },
  {
    "id": "tshirt-girls-140",
    "slug": "girls-green-henley-12",
    "category": "t-shirts",
    "title": "Green Henley",
    "description": "Slim Fit green henley for girls",
    "price": 16.71,
    "color": "green",
    "size": "XS",
    "gender": "girls",
    "popularity": 76
  },
  {
    "id": "tshirt-girls-141",
    "slug": "girls-gray-polo-13",
    "category": "t-shirts",
    "title": "Gray Polo",
    "description": "Regular Fit gray polo for girls",
    "price": 24.14,
    "color": "gray",
    "size": "S",
    "gender": "girls",
    "popularity": 74
  },
  {
    "id": "tshirt-boys-142",
    "slug": "boys-black-crew-neck-0",
    "category": "t-shirts",
    "title": "Black Crew Neck",
    "description": "Slim Fit black crew neck for boys",
    "price": 25.4,
    "color": "black",
    "size": "XS",
    "gender": "boys",
    "popularity": 63
  },
  {
    "id": "tshirt-boys-143",
    "slug": "boys-white-v-neck-1",
    "category": "t-shirts",
    "title": "White V-Neck",
    "description": "Regular Fit white v-neck for boys",
    "price": 18.31,
    "color": "white",
    "size": "S",
    "gender": "boys",
    "popularity": 72
  },
  {
    "id": "tshirt-boys-144",
    "slug": "boys-blue-henley-2",
    "category": "t-shirts",
    "title": "Blue Henley",
    "description": "Relaxed Fit blue henley for boys",
    "price": 25.24,
    "color": "blue",
    "size": "M",
    "gender": "boys",
    "popularity": 83
  },
  {
    "id": "tshirt-boys-145",
    "slug": "boys-red-polo-3",
    "category": "t-shirts",
    "title": "Red Polo",
    "description": "Athletic Fit red polo for boys",
    "price": 18.24,
    "color": "red",
    "size": "L",
    "gender": "boys",
    "popularity": 90
  },
  {
    "id": "tshirt-boys-146",
    "slug": "boys-green-tank-top-4",
    "category": "t-shirts",
    "title": "Green Tank Top",
    "description": "Slim Fit green tank top for boys",
    "price": 18.42,
    "color": "green",
    "size": "XS",
    "gender": "boys",
    "popularity": 55
  },
  {
    "id": "tshirt-boys-147",
    "slug": "boys-gray-crew-neck-5",
    "category": "t-shirts",
    "title": "Gray Crew Neck",
    "description": "Regular Fit gray crew neck for boys",
    "price": 18.42,
    "color": "gray",
    "size": "S",
    "gender": "boys",
    "popularity": 65
  },
  {
    "id": "tshirt-boys-148",
    "slug": "boys-brown-v-neck-6",
    "category": "t-shirts",
    "title": "Brown V-Neck",
    "description": "Relaxed Fit brown v-neck for boys",
    "price": 19.89,
    "color": "brown",
    "size": "M",
    "gender": "boys",
    "popularity": 88
  },
  {
    "id": "tshirt-boys-149",
    "slug": "boys-tan-henley-7",
    "category": "t-shirts",
    "title": "Tan Henley",
    "description": "Athletic Fit tan henley for boys",
    "price": 17.86,
    "color": "tan",
    "size": "L",
    "gender": "boys",
    "popularity": 89
  },
  {
    "id": "tshirt-boys-150",
    "slug": "boys-black-polo-8",
    "category": "t-shirts",
    "title": "Black Polo",
    "description": "Slim Fit black polo for boys",
    "price": 22.59,
    "color": "black",
    "size": "XS",
    "gender": "boys",
    "popularity": 94
  },
  {
    "id": "tshirt-boys-151",
    "slug": "boys-white-tank-top-9",
    "category": "t-shirts",
    "title": "White Tank Top",
    "description": "Regular Fit white tank top for boys",
    "price": 16.52,
    "color": "white",
    "size": "S",
    "gender": "boys",
    "popularity": 91
  },
  {
    "id": "tshirt-boys-152",
    "slug": "boys-blue-crew-neck-10",
    "category": "t-shirts",
    "title": "Blue Crew Neck",
    "description": "Relaxed Fit blue crew neck for boys",
    "price": 17.1,
    "color": "blue",
    "size": "M",
    "gender": "boys",
    "popularity": 82
  },
  {
    "id": "tshirt-boys-153",
    "slug": "boys-red-v-neck-11",
    "category": "t-shirts",
    "title": "Red V-Neck",
    "description": "Athletic Fit red v-neck for boys",
    "price": 22.57,
    "color": "red",
    "size": "L",
    "gender": "boys",
    "popularity": 85
  },
  {
    "id": "tshirt-boys-154",
    "slug": "boys-green-henley-12",
    "category": "t-shirts",
    "title": "Green Henley",
    "description": "Slim Fit green henley for boys",
    "price": 21.43,
    "color": "green",
    "size": "XS",
    "gender": "boys",
    "popularity": 65
  },
  {
    "id": "tshirt-boys-155",
    "slug": "boys-gray-polo-13",
    "category": "t-shirts",
    "title": "Gray Polo",
    "description": "Regular Fit gray polo for boys",
    "price": 24.81,
    "color": "gray",
    "size": "S",
    "gender": "boys",
    "popularity": 92
  }
]